is_even/__init__.py
is_even/_py2_is_even.py
is_even/_py3_10_is_even.py
is_even/_py3_8_is_even.py
is_even/_py3_api_response.py
is_even/_py3_is_even.py
is_even/_py_api_exception.py
is_even/_typings.py
is_even/is_even.py
PyIsEven-0.8.12.dist-info/LICENSE
PyIsEven-0.8.12.dist-info/METADATA
PyIsEven-0.8.12.dist-info/WHEEL
PyIsEven-0.8.12.dist-info/top_level.txt
PyIsEven-0.8.12.dist-info/RECORD
