Metadata-Version: 2.1
Name: PyIsEven
Version: 0.8.12
Summary: Check is a integer is even
Home-page: https://github.com/rosineygp/PyIsEven
Author: Rosiney Gomes Pereira
License: MIT
Keywords: even
License-File: LICENSE
Requires-Dist: requests >=2.14.0
Requires-Dist: retry >=0.9.2
Requires-Dist: typing-extensions >=3.10.0.0
